{
  "calories": 420,
  "cooking_time_minutes": 12,
  "ingredients": [
    {
      "count": 2,
      "ingredient": "eggs"
    },
    {
      "count": 2,
      "ingredient": "slices of bread"
    },
    {
      "count": 1,
      "ingredient": "tablespoon of mayonnaise"
    },
    {
      "count": 1,
      "ingredient": "tablespoon of ketchup (optional)"
    }
  ],
  "recipe": "Quick Egg Salad Sandwich",
  "steps": [
    "Hard boil two eggs. Once cooked, cool them under cold water, peel, and chop them into small pieces.",
    "Toast two slices of bread to your desired crispness.",
    "In a small bowl, combine the chopped eggs with mayonnaise, mixing well.",
    "Spread the egg mixture evenly over one slice of toasted bread.",
    "If desired, drizzle ketchup over the egg mixture.",
    "Place the second slice of toasted bread on top to complete the sandwich. Serve immediately."
  ]
}